airflow_impatient/hooks/__init__.py
airflow_impatient/hooks/ibm_cos_hook.py
airflow_impatient/logging/__init__.py
airflow_impatient/logging/airflow_logging.py
airflow_impatient/logging/file_task_handler.py
airflow_impatient/operators/__init__.py
airflow_impatient/operators/spark_submit_operator.py
airflow_impatient-0.0.1.dist-info/METADATA
airflow_impatient-0.0.1.dist-info/WHEEL
airflow_impatient-0.0.1.dist-info/top_level.txt
airflow_impatient-0.0.1.dist-info/RECORD
